orange_newton/__init__.py
orange_newton/check_python.py
orange_newton/main.py
orange_newton-0.0.14.dist-info/METADATA
orange_newton-0.0.14.dist-info/WHEEL
orange_newton-0.0.14.dist-info/licenses/LICENSE
orange_newton-0.0.14.dist-info/RECORD
