Metadata-Version: 2.4
Name: orange_newton
Version: 0.0.14
Summary: A Simple Orange Newton Project
Author-email: Hiroshi Fujiwara <hiroshi.829f@gmail.com>
License: MIT License
License-File: LICENSE
Classifier: Programming Language :: Python
Classifier: Programming Language :: Python :: 3
Classifier: Programming Language :: Python :: 3.13
Classifier: Topic :: Software Development :: Libraries :: Python Modules
Requires-Python: >=3.13
